prcpy/__init__.py
prcpy/DataHandling/__init__.py
prcpy/DataHandling/File_handlers.py
prcpy/DataHandling/Path_handlers.py
prcpy/main.py
prcpy/Maths/__init__.py
prcpy/Maths/Maths_functions.py
prcpy/Maths/Target_functions.py
prcpy/Plots/__init__.py
prcpy/Plots/Plot_RC.py
prcpy/RC/__init__.py
prcpy/RC/Perform_RC.py
prcpy/RC/Pipeline_RC.py
prcpy/RC/Prepare_RC.py
prcpy/TrainingModels/__init__.py
prcpy/TrainingModels/RegressionModels.py
prcpy/Utilities/__init__.py
prcpy/Utilities/os_check.py
prcpy/Utilities/sorting.py
prcpy-0.1.14.dist-info/LICENSE
prcpy-0.1.14.dist-info/METADATA
prcpy-0.1.14.dist-info/WHEEL
prcpy-0.1.14.dist-info/RECORD
